[{"meta": {"id": "bloodstone", "uuid": "d320afd9-b5ff-4b2d-865f-1903f739e7aa", "sort": "020290500", "src": "collegiate", "section": "alpha", "stems": ["bloodstone", "bloodstones", "heliotrope"], "offensive": false}, "hwi": {"hw": "blood*stone", "prs": [{"mw": "\u02c8bl\u0259d-\u02ccst\u014dn", "sound": {"audio": "bloods06", "ref": "c", "stat": "1"}}]}, "fl": "noun", "def": [{"sseq": [[["sense", {"dt": [["text", "{bc}a green chalcedony sprinkled with red spots resembling {a_link|blood} "], ["ca", {"intro": "called also", "cats": [{"cat": "heliotrope"}]}]]}]]]}], "date": "1504", "shortdef": ["a green chalcedony sprinkled with red spots resembling blood \u2014called also heliotrope"]}]