[{"meta": {"id": "cereal:1", "uuid": "bbcde257-56ac-475f-8073-431b1dfa5d97", "sort": "031855000", "src": "collegiate", "section": "alpha", "stems": ["cereal"], "offensive": false}, "hom": 1, "hwi": {"hw": "ce*re*al", "prs": [{"mw": "\u02c8sir-\u0113-\u0259l", "sound": {"audio": "cereal01", "ref": "c", "stat": "1"}}]}, "fl": "adjective", "def": [{"sseq": [[["sense", {"dt": [["text", "{bc}relating to grain or to the plants that produce it"]], "sdsense": {"sd": "also", "dt": [["text", "{bc}made of grain"]]}}]]]}], "et": [["text", "borrowed from French & Latin; French {it}c\u00e9r\u00e9ale,{/it} borrowed from Latin {it}Ceri\u0101lis, Cere\u0101lis{/it} \"of the goddess Ceres, of wheat or bread,\" from {it}Cerer-, Cer\u0113s{/it} {et_link|ceres|Ceres} + {it}-\u0101lis{/it} {et_link|-al:1|-al:1}"], ["et_snote", [["t", "The derivation of {it}Ceri\u0101lis, Cere\u0101lis{/it} is unclear, as formation directly from the noun does not look possible. M. Leumann ({it}Lateinische Laut- und Formenlehre,{/it} Munich, 1977, p. 180) suggests as the base an earlier {it}*Cerrius,{/it} from {it}*Cerzios,{/it} syncopated from a possessive adjective {it}*Cerez-ios.{/it} A putative {it}*Cerri\u0101lis{/it} would have been re-formed to {it}Ceri\u0101lis,{/it} then {it}Cere\u0101lis,{/it} after {it}Cer\u0113s.{/it}"]]]], "date": "1818", "shortdef": ["relating to grain or to the plants that produce it; also : made of grain"]}, {"meta": {"id": "cereal:2", "uuid": "1d8403cf-fac0-4ed7-a163-cbac4ecc7a22", "sort": "031856000", "src": "collegiate", "section": "alpha", "stems": ["cereal", "cereals"], "offensive": false}, "hom": 2, "hwi": {"hw": "cereal"}, "fl": "noun", "def": [{"sseq": [[["sense", {"sn": "1", "dt": [["text", "{bc}a plant (such as a grass) yielding starchy grain suitable for food"]], "sdsense": {"sd": "also", "dt": [["text", "{bc}its grain"]]}}]], [["sense", {"sn": "2", "dt": [["text", "{bc}a prepared foodstuff of grain (such as oatmeal or cornflakes)"]]}]]]}], "et": [["text", "derivative of {et_link|cereal:1|cereal:1}"]], "date": "1832{ds||1||}", "shortdef": ["a plant (such as a grass) yielding starchy grain suitable for food; also : its grain", "a prepared foodstuff of grain (such as oatmeal or cornflakes)"]}, {"meta": {"id": "cereal leaf beetle", "uuid": "e42aa009-0f9e-40ce-b066-993aca116497", "sort": "031857000", "src": "collegiate", "section": "alpha", "stems": ["cereal leaf beetle", "cereal leaf beetles"], "offensive": false}, "hwi": {"hw": "cereal leaf beetle"}, "fl": "noun", "def": [{"sseq": [[["sense", {"dt": [["text", "{bc}a small reddish-brown black-headed Old World chrysomelid beetle ({it}Oulema melanopus{/it}) that feeds on cereal grasses and is a serious pest of U.S. grain crops"]]}]]]}], "date": "1962", "shortdef": ["a small reddish-brown black-headed Old World chrysomelid beetle (Oulema melanopus) that feeds on cereal grasses and is a serious pest of U.S. grain crops"]}]