[{"meta": {"id": "exchange:2", "uuid": "785d8746-68b0-4835-b882-9f8abadf1c54", "sort": "050258600", "src": "collegiate", "section": "alpha", "stems": ["exchange", "exchangeabilities", "exchangeability", "exchangeable", "exchanged", "exchanger", "exchangers", "exchanges", "exchanging"], "offensive": false}, "hom": 2, "hwi": {"hw": "exchange"}, "fl": "verb", "ins": [{"if": "ex*changed"}, {"if": "ex*chang*ing"}], "def": [{"vd": "transitive verb", "sseq": [[["sense", {"sn": "1 a", "dt": [["text", "{bc}to part with, give, or transfer in consideration of something received as an equivalent"]]}], ["sense", {"sn": "b", "dt": [["text", "{bc}to have replaced by other merchandise "], ["vis", [{"t": "{it}exchanged{/it} the shirt for one in a larger size"}]]]}]], [["sense", {"sn": "2", "dt": [["text", "{bc}to part with for a substitute "], ["vis", [{"t": "{it}exchanging{/it} future security for immediate pleasure"}]]]}]], [["sense", {"sn": "3", "dt": [["text", "{bc}to give and receive reciprocally "], ["vis", [{"t": "{wi}exchange{/wi} gifts"}]]]}]]]}, {"vd": "intransitive verb", "sseq": [[["sense", {"sn": "1", "dt": [["text", "{bc}to pass or become received in exchange"]]}]], [["sense", {"sn": "2", "dt": [["text", "{bc}to engage in an exchange"]]}]]]}], "uros": [{"ure": "ex*change*abil*i*ty", "prs": [{"mw": "iks-\u02ccch\u0101n-j\u0259-\u02c8bi-l\u0259-t\u0113", "sound": {"audio": "exchan03", "ref": "c", "stat": "1"}}], "fl": "noun"}, {"ure": "ex*change*able", "prs": [{"mw": "iks-\u02c8ch\u0101n-j\u0259-b\u0259l", "sound": {"audio": "exchan04", "ref": "c", "stat": "1"}}], "fl": "adjective"}, {"ure": "ex*chang*er", "prs": [{"mw": "iks-\u02c8ch\u0101n-j\u0259r", "sound": {"audio": "exchan05", "ref": "c", "stat": "1"}}, {"mw": "\u02c8eks-\u02ccch\u0101n-"}], "fl": "noun"}], "date": "15th century{ds|t|1|a|}", "shortdef": ["to part with, give, or transfer in consideration of something received as an equivalent", "to have replaced by other merchandise", "to part with for a substitute"]}]