[{"meta": {"id": "forelimb", "uuid": "beee22ef-b562-402c-a2fb-9c8db7934903", "sort": "062607000", "src": "collegiate", "section": "alpha", "stems": ["forelimb", "forelimbs"], "offensive": false}, "hwi": {"hw": "fore*limb", "prs": [{"mw": "\u02c8f\u022fr-\u02cclim", "sound": {"audio": "foreli01", "ref": "c", "stat": "1"}}]}, "fl": "noun", "def": [{"sseq": [[["sense", {"dt": [["text", "{bc}a limb (such as an arm, wing, fin, or leg) that is situated anteriorly "], ["vis", [{"t": "the {wi}forelimb{/wi} of a bat"}]]]}]]]}], "date": "circa 1796", "shortdef": ["a limb (such as an arm, wing, fin, or leg) that is situated anteriorly"]}]