[{"meta": {"id": "gammon:1", "uuid": "246f4ed3-dcff-4871-8583-c41cb183a21c", "sort": "070264000", "src": "collegiate", "section": "alpha", "stems": ["gammon", "gammons"], "offensive": false}, "hom": 1, "hwi": {"hw": "gam*mon", "prs": [{"mw": "\u02c8ga-m\u0259n", "sound": {"audio": "gammon01", "ref": "c", "stat": "1"}}]}, "fl": "noun", "def": [{"sseq": [[["sense", {"sn": "1", "sls": ["chiefly British"], "dt": [["text", "{bc}{sx|ham||2}"]]}]], [["sen", {"sn": "2", "sls": ["chiefly British"]}], ["sense", {"sn": "a", "dt": [["text", "{bc}a side of bacon"]]}], ["sense", {"sn": "b", "dt": [["text", "{bc}the lower end of a side of bacon"]]}]]]}], "et": [["text", "assimilated form of earlier {it}gambon{/it}, borrowed from Anglo-French {it}gamboun, jaumbeun{/it}, from {it}gambe, jambe{/it} \"hock of a horse, leg\" + {it}-on{/it}, diminutive or particularizing suffix, going back to Latin {it}-\u014d, -\u014dn-{/it}, suffix of persons with a prominent feature {ma}{mat|jamb|}{/ma}"]], "date": "15th century{ds||1||}", "shortdef": ["ham", "a side of bacon", "the lower end of a side of bacon"]}, {"meta": {"id": "gammon:2", "uuid": "72db314e-5d4f-44cc-b4b0-60d911f2da04", "sort": "070265000", "src": "collegiate", "section": "alpha", "stems": ["gammon", "gammons"], "offensive": false}, "hom": 2, "hwi": {"hw": "gammon"}, "fl": "noun", "def": [{"sseq": [[["sense", {"sn": "1", "sls": ["archaic"], "dt": [["text", "{bc}{sx|backgammon||}"]]}]], [["sense", {"sn": "2", "dt": [["text", "{bc}the winning of a backgammon game before the loser removes any men from the board"]]}]]]}], "et": [["text", "probably shortened from {et_link|backgammon|backgammon}"]], "date": "1699{ds||1||}", "shortdef": ["backgammon", "the winning of a backgammon game before the loser removes any men from the board"]}, {"meta": {"id": "gammon:3", "uuid": "c6d2ccab-6cac-410d-85fa-ccee8775de63", "sort": "070266000", "src": "collegiate", "section": "alpha", "stems": ["gammon", "gammoned", "gammoning", "gammons"], "offensive": false}, "hom": 3, "hwi": {"hw": "gammon"}, "fl": "verb", "ins": [{"if": "gam*moned"}, {"if": "gam*mon*ing"}, {"if": "gam*mons"}], "def": [{"vd": "transitive verb", "sseq": [[["sense", {"dt": [["text", "{bc}to beat by scoring a gammon"]]}]]]}], "et": [["text", "derivative of {et_link|gammon:2|gammon:2}"]], "date": "1668", "shortdef": ["to beat by scoring a gammon"]}, {"meta": {"id": "gammon:4", "uuid": "4ce864df-6daa-4b23-87f9-a171c3ddecb4", "sort": "070267000", "src": "collegiate", "section": "alpha", "stems": ["gammon", "gammoned", "gammoning", "gammons"], "offensive": false}, "hom": 4, "hwi": {"hw": "gammon"}, "fl": "verb", "ins": [{"if": "gam*moned"}, {"if": "gam*mon*ing"}, {"if": "gam*mons"}], "def": [{"vd": "intransitive verb", "sseq": [[["sense", {"sn": "1", "dt": [["text", "{bc}to talk gammon"]]}]], [["sense", {"sn": "2", "dt": [["text", "{bc}{sx|pretend||}, {sx|feign||}"]]}]]]}, {"vd": "transitive verb", "sseq": [[["sense", {"dt": [["text", "{bc}{sx|deceive||}, {sx|fool||}"]]}]]]}], "et": [["text", "derivative of {et_link|gammon:5|gammon:5}"]], "date": "1781{ds|i|1||}", "shortdef": ["to talk gammon", "pretend, feign", "deceive, fool"]}, {"meta": {"id": "gammon:5", "uuid": "a0797e9e-f6ba-4edc-8193-64f6965ace76", "sort": "070268000", "src": "collegiate", "section": "alpha", "stems": ["gammon", "gammons"], "offensive": false}, "hom": 5, "hwi": {"hw": "gammon"}, "fl": "noun", "def": [{"sseq": [[["sense", {"dt": [["text", "{bc}talk intended to deceive"]]}]]]}], "et": [["text", "argot word, earlier in sense \"criminal accomplice who distracts a victim during a robbery,\" of uncertain origin"]], "date": "1781", "shortdef": ["talk intended to deceive"]}]