[{"meta": {"id": "humanoid:1", "uuid": "05bb3ffc-a595-4582-bba1-2dee5e7ba4c3", "sort": "080301300", "src": "collegiate", "section": "alpha", "stems": ["humanoid"], "offensive": false}, "hom": 1, "hwi": {"hw": "hu*man*oid", "prs": [{"mw": "\u02c8hy\u00fc-m\u0259-\u02ccn\u022fid", "sound": {"audio": "humano01", "ref": "c", "stat": "1"}}, {"mw": "\u02c8y\u00fc-"}]}, "fl": "adjective", "def": [{"sseq": [[["sense", {"dt": [["text", "{bc}having {a_link|human} form or characteristics "], ["vis", [{"t": "{wi}humanoid{/wi} dentition"}, {"t": "{wi}humanoid{/wi} robots"}]]]}]]]}], "date": "1918", "shortdef": ["having human form or characteristics"]}, {"meta": {"id": "humanoid:2", "uuid": "207f98bf-c175-4a22-ae90-1a6f1cc6106b", "sort": "080301350", "src": "collegiate", "section": "alpha", "stems": ["humanoid", "humanoids"], "offensive": false}, "hom": 2, "hwi": {"hw": "humanoid"}, "fl": "noun", "ins": [{"il": "plural", "if": "hu*man*oids"}], "def": [{"sseq": [[["sense", {"dt": [["text", "{bc}a {d_link|humanoid|humanoid:1} being {bc}a nonhuman creature or being with characteristics (such as the ability to walk upright) resembling those of a human "], ["vis", [{"t": "Why do people respond so strongly to penguins? First, they stand straight and walk upright, like us, so we see them as little {wi}humanoids{/wi}\u2014a convention of headwaiters, ten thousand nuns, plump babies in snowsuits.", "aq": {"auth": "Diane Ackerman"}}, {"t": "Those tales of the deep blended narratives of voyages of exploration \u2026 with fantastic additions drawn from an ancient repertoire of sea monsters and mutant {wi}humanoids{/wi}.", "aq": {"auth": "Simon Schama"}}]]]}]]]}], "date": "1870", "shortdef": ["a humanoid being : a nonhuman creature or being with characteristics (such as the ability to walk upright) resembling those of a human"]}]