[{"meta": {"id": "irreverent", "uuid": "583a30f8-c840-49a5-a6fa-04021dda8733", "sort": "092964000", "src": "collegiate", "section": "alpha", "stems": ["irreverent", "irreverently"], "offensive": false}, "hwi": {"hw": "ir*rev*er*ent", "prs": [{"mw": "i-\u02c8rev-r\u0259nt", "sound": {"audio": "irreve02", "ref": "c", "stat": "1"}}, {"mw": "\u02cci(r)-"}, {"mw": "-\u02c8re-v\u0259-", "pun": ";"}, {"mw": "-\u02c8re-v\u0259rnt"}]}, "fl": "adjective", "def": [{"sseq": [[["sense", {"dt": [["text", "{bc}lacking proper respect or seriousness"]], "sdsense": {"sd": "also", "dt": [["text", "{bc}{sx|satiric||}"]]}}]]]}], "uros": [{"ure": "ir*rev*er*ent*ly", "fl": "adverb"}], "et": [["text", "Middle English, from Latin {it}irreverent-, irreverens{/it}, from {it}in-{/it} + {it}reverent-, reverens{/it} reverent"]], "date": "15th century", "shortdef": ["lacking proper respect or seriousness; also : satiric"]}]