[{"meta": {"id": "loving", "uuid": "1ba4de2a-ec88-4482-9a73-8aaf655917be", "sort": "120265200", "src": "collegiate", "section": "alpha", "stems": ["loving", "lovingly", "lovingness", "lovingnesses"], "offensive": false}, "hwi": {"hw": "lov*ing", "prs": [{"mw": "\u02c8l\u0259-vi\u014b", "sound": {"audio": "loving01", "ref": "c", "stat": "1"}}]}, "fl": "adjective", "def": [{"sseq": [[["sense", {"sn": "1", "dt": [["text", "{bc}{sx|affectionate||}"]]}]], [["sense", {"sn": "2", "dt": [["text", "{bc}{sx|painstaking||}"]]}]]]}], "uros": [{"ure": "lov*ing*ly", "prs": [{"mw": "\u02c8l\u0259-vi\u014b-l\u0113", "sound": {"audio": "loving02", "ref": "c", "stat": "1"}}], "fl": "adverb"}, {"ure": "lov*ing*ness", "fl": "noun"}], "date": "before 12th century{ds||1||}", "shortdef": ["affectionate", "painstaking"]}]