[{"meta": {"id": "mordant:1", "uuid": "0ab0c262-ffa7-4a7f-94db-5fb85083e583", "sort": "134012000", "src": "collegiate", "section": "alpha", "stems": ["mordant", "mordantly"], "offensive": false}, "hom": 1, "hwi": {"hw": "mor*dant", "prs": [{"mw": "\u02c8m\u022fr-d\u1d4ant", "sound": {"audio": "mordan02", "ref": "c", "stat": "1"}}]}, "fl": "adjective", "def": [{"sseq": [[["sense", {"sn": "1", "dt": [["text", "{bc}biting and caustic in thought, manner, or style {bc}{sx|incisive||} "], ["vis", [{"t": "a {wi}mordant{/wi} wit"}]]]}]], [["sense", {"sn": "2", "dt": [["text", "{bc}acting as a {d_link|mordant|mordant:2} (as in dyeing)"]]}]], [["sense", {"sn": "3", "dt": [["text", "{bc}{sx|burning||}, {sx|pungent||} "], ["vis", [{"t": "{wi}mordant{/wi} pain"}]]]}]]]}], "uros": [{"ure": "mor*dant*ly", "fl": "adverb"}], "syns": [{"pl": "synonyms", "pt": [["text", "{sc}caustic{/sc} {sc}mordant{/sc} {sc}acrid{/sc} {sc}scathing{/sc} mean stingingly incisive. {sc}caustic{/sc} suggests a biting wit. "], ["vis", [{"t": "{it}caustic{/it} comments"}]], ["text", " {sc}mordant{/sc} suggests a wit that is used with deadly effectiveness. "], ["vis", [{"t": "{it}mordant{/it} reviews of the play"}]], ["text", " {sc}acrid{/sc} implies bitterness and often malevolence. "], ["vis", [{"t": "{it}acrid{/it} invective"}]], ["text", " {sc}scathing{/sc} implies indignant attacks delivered with fierce severity. "], ["vis", [{"t": "a {it}scathing{/it} satire"}]]]}], "et": [["text", "Middle French, present participle of {it}mordre{/it} to bite, from Latin {it}mord\u0113re{/it}; perhaps akin to Sanskrit {it}m\u1e5bdn\u0101ti{/it} he presses, rubs"]], "date": "15th century{ds||1||}", "shortdef": ["biting and caustic in thought, manner, or style : incisive", "acting as a mordant (as in dyeing)", "burning, pungent"]}, {"meta": {"id": "mordant:2", "uuid": "0dabd74c-5ae2-4860-8d31-a83be1e5bce6", "sort": "134013000", "src": "collegiate", "section": "alpha", "stems": ["mordant", "mordants", "mordent"], "offensive": false}, "hom": 2, "hwi": {"hw": "mordant"}, "fl": "noun", "def": [{"sseq": [[["sense", {"sn": "1", "dt": [["text", "{bc}a chemical that fixes a dye in or on a substance by combining with the dye to form an insoluble compound"]]}]], [["sense", {"sn": "2", "dt": [["text", "{bc}a corroding substance used in etching"]]}]]]}], "et": [["text", "{dx_ety}see {dxt|mordant:1||}{/dx_ety}"]], "date": "1791{ds||1||}", "shortdef": ["a chemical that fixes a dye in or on a substance by combining with the dye to form an insoluble compound", "a corroding substance used in etching"]}, {"meta": {"id": "mordant:3", "uuid": "fd869d0b-eb0a-426f-a405-c89c0283b443", "sort": "134014000", "src": "collegiate", "section": "alpha", "stems": ["mordant", "mordanted", "mordanting", "mordants"], "offensive": false}, "hom": 3, "hwi": {"hw": "mordant"}, "fl": "verb", "ins": [{"if": "mor*dant*ed"}, {"if": "mor*dant*ing"}, {"if": "mor*dants"}], "def": [{"vd": "transitive verb", "sseq": [[["sense", {"dt": [["text", "{bc}to treat with a mordant"]]}]]]}], "date": "1836", "shortdef": ["to treat with a mordant"]}]