[{"meta": {"id": "must:1", "uuid": "ec623ae3-261b-4040-93a2-8260b08f133d", "sort": "134933000", "src": "collegiate", "section": "alpha", "stems": ["must"], "offensive": false}, "hom": 1, "hwi": {"hw": "must", "prs": [{"mw": "m\u0259s(t)"}, {"mw": "\u02c8m\u0259st", "sound": {"audio": "must0001", "ref": "c", "stat": "1"}}]}, "fl": "verb", "ins": [{"il": "present tense and past tense, all persons", "if": "must"}], "def": [{"vd": "auxiliary verb", "sseq": [[["sense", {"sn": "1 a", "dt": [["text", "{bc}be commanded or requested to "], ["vis", [{"t": "you {wi}must{/wi} stop"}]]]}], ["sense", {"sn": "b", "dt": [["text", "{bc}be urged to {bc}ought by all means to "], ["vis", [{"t": "you {wi}must{/wi} read that book"}]]]}]], [["sense", {"sn": "2", "dt": [["text", "{bc}be compelled by physical necessity to "], ["vis", [{"t": "one {wi}must{/wi} eat to live"}]], ["text", " {bc}be required by immediate or future need or purpose to "], ["vis", [{"t": "we {wi}must{/wi} hurry to catch the bus"}]]]}]], [["sense", {"sn": "3 a", "dt": [["text", "{bc}be obliged to {bc}be compelled by social considerations to "], ["vis", [{"t": "I {wi}must{/wi} say you're looking well"}]]]}], ["sense", {"sn": "b", "dt": [["text", "{bc}be required by law, custom, or moral conscience {dx_def}see {dxt|conscience||1}{/dx_def} to "], ["vis", [{"t": "we {wi}must{/wi} obey the rules"}]]]}], ["sense", {"sn": "c", "dt": [["text", "{bc}be determined to "], ["vis", [{"t": "if you {wi}must{/wi} go at least wait for me"}]]]}], ["sense", {"sn": "d", "dt": [["text", "{bc}be unreasonably or {d_link|perversely|perverse} compelled to "], ["vis", [{"t": "why {wi}must{/wi} you argue"}]]]}]], [["sense", {"sn": "4", "dt": [["text", "{bc}be logically inferred {dx_def}see {dxt|infer||1}{/dx_def} or supposed to "], ["vis", [{"t": "it {wi}must{/wi} be time"}]]]}]], [["sense", {"sn": "5", "dt": [["text", "{bc}be compelled by fate or by {d_link|natural law|natural law} to "], ["vis", [{"t": "what {wi}must{/wi} be will be"}]]]}]], [["sense", {"sn": "6", "dt": [["text", "{bc}was or were {d_link|presumably|presumably} certain to {bc}was or were bound to "], ["vis", [{"t": "if he did it she {wi}must{/wi} have known"}]]]}]], [["sense", {"sn": "7", "sls": ["dialect"], "dt": [["text", "{bc}{sx|may||}, {sx|shall||} "], ["uns", [[["text", "used chiefly in questions"]]]]]}]]]}, {"vd": "intransitive verb", "sseq": [[["sense", {"sls": ["archaic"], "dt": [["text", "{bc}to be obliged to go "], ["vis", [{"t": "I {wi}must{/wi} to Coventry", "aq": {"auth": "William Shakespeare"}}]]]}]]]}], "et": [["text", "Middle English {it}moste{/it}, from Old English {it}m\u014dste{/it}, past indicative & subjunctive of {it}m\u014dtan{/it} to be allowed to, have to; akin to Old High German {it}muozan{/it} to be allowed to, have to"]], "date": "before 12th century{ds|aux|1|a|}", "shortdef": ["be commanded or requested to", "be urged to : ought by all means to", "be compelled by physical necessity to : be required by immediate or future need or purpose to"]}, {"meta": {"id": "must:2", "uuid": "529cd0d2-1800-4c20-8641-d994c221eb93", "sort": "134934000", "src": "collegiate", "section": "alpha", "stems": ["must", "musth", "musts"], "offensive": false}, "hom": 2, "hwi": {"hw": "must", "prs": [{"mw": "\u02c8m\u0259st", "sound": {"audio": "must0001", "ref": "c", "stat": "1"}}]}, "fl": "noun", "def": [{"sseq": [[["sense", {"sn": "1", "dt": [["text", "{bc}an imperative need or duty {bc}{sx|requirement||}"]]}]], [["sense", {"sn": "2", "dt": [["text", "{bc}an indispensable item {bc}{sx|essential||} "], ["vis", [{"t": "exercise is a {wi}must{/wi}"}]]]}]]]}], "et": [["text", "{dx_ety}see {dxt|must:1||}{/dx_ety}"]], "date": "1598{ds||1||}", "shortdef": ["an imperative need or duty : requirement", "an indispensable item : essential"]}, {"meta": {"id": "must:3", "uuid": "2f5471de-ac36-48b6-b703-5459459d9c5e", "sort": "134935000", "src": "collegiate", "section": "alpha", "stems": ["must", "musth", "musts"], "offensive": false}, "hom": 3, "hwi": {"hw": "must"}, "fl": "noun", "def": [{"sseq": [[["sense", {"dt": [["text", "{bc}the expressed juice of fruit and especially grapes before and during fermentation"]], "sdsense": {"sd": "also", "dt": [["text", "{bc}the pulp and skins of the crushed grapes"]]}}]]]}], "et": [["text", "Middle English, from Old English, from Latin {it}mustum{/it}"]], "date": "before 12th century", "shortdef": ["the expressed juice of fruit and especially grapes before and during fermentation; also : the pulp and skins of the crushed grapes"]}, {"meta": {"id": "must:4", "uuid": "e7b4490d-194e-4879-9b0c-ebe1c38f0eaf", "sort": "134936000", "src": "collegiate", "section": "alpha", "stems": ["must", "musth", "musts"], "offensive": false}, "hom": 4, "hwi": {"hw": "must"}, "fl": "noun", "def": [{"sseq": [[["sense", {"sn": "1", "dt": [["text", "{bc}{sx|musk||}"]]}]], [["sense", {"sn": "2", "dt": [["text", "{bc}{sx|mold:3||}, {sx|mustiness||}"]]}]]]}], "et": [["text", "Middle English (Scots) {it}moist{/it}, from Middle French {it}must{/it}, alteration of {it}musc{/it} musk"]], "date": "15th century{ds||1||}", "shortdef": ["musk", "mold, mustiness"]}, {"meta": {"id": "musth", "uuid": "d4923baf-36f3-4287-a40d-fdcdfa65c264", "sort": "134947000", "src": "collegiate", "section": "alpha", "stems": ["must", "musth", "musths", "musts"], "offensive": false}, "hwi": {"hw": "musth", "prs": [{"mw": "\u02c8m\u0259st", "sound": {"audio": "musth001", "ref": "c", "stat": "1"}}]}, "vrs": [{"vl": "or less commonly", "va": "must"}], "fl": "noun", "def": [{"sseq": [[["sense", {"dt": [["text", "{bc}a periodic state of the bull elephant characterized especially by aggressive behavior and usually connected with the rutting season"]]}]]]}], "et": [["text", "Hindi & Urdu {it}mast{/it} intoxicated, from Persian"]], "date": "1878", "shortdef": ["a periodic state of the bull elephant characterized especially by aggressive behavior and usually connected with the rutting season"]}, {"meta": {"id": "must-have", "uuid": "62b65b4f-9860-4527-80f7-c477168eff0a", "sort": "134948000", "src": "collegiate", "section": "alpha", "stems": ["must-have", "must-haves"], "offensive": false}, "hwi": {"hw": "must-have", "prs": [{"mw": "\u02c8m\u0259st-\u02cchav", "sound": {"audio": "musth01v", "ref": "c", "stat": "1"}}]}, "fl": "noun", "def": [{"sseq": [[["sense", {"dt": [["text", "{bc}something that is essential to have or obtain"]]}]]]}], "uros": [{"ure": "must-have", "fl": "adjective"}], "date": "1839", "shortdef": ["something that is essential to have or obtain"]}, {"meta": {"id": "must-see", "uuid": "f773a933-28be-433a-b05a-95cca274b019", "sort": "134950000", "src": "collegiate", "section": "alpha", "stems": ["must-see", "must-sees"], "offensive": false}, "hwi": {"hw": "must-see", "prs": [{"mw": "\u02c8m\u0259st-\u02c8s\u0113", "sound": {"audio": "mustse01", "ref": "c", "stat": "1"}}]}, "fl": "noun", "def": [{"sseq": [[["sense", {"dt": [["text", "{bc}something (such as a film) that must or should be seen"]]}]]]}], "uros": [{"ure": "must-see", "fl": "adjective"}], "date": "1936", "shortdef": ["something (such as a film) that must or should be seen"]}, {"meta": {"id": "if someone must", "uuid": "d8434478-7ec3-45ae-b86b-e448baed5e98", "sort": "3009162000", "src": "ld", "section": "idioms", "stems": ["if someone must"], "offensive": false}, "hwi": {"hw": "if someone must"}, "fl": "idiom", "def": [{"sseq": [[["sense", {"dt": [["uns", [[["text", "used to say that one will allow someone to do something even though one does not approve of it "], ["vis", [{"t": "He can smoke {it}if he must{/it}, but he has to do it outdoors."}]]]]]]}]]]}], "shortdef": ["\u2014used to say that one will allow someone to do something even though one does not approve of it"]}, {"meta": {"id": "if you must know", "uuid": "9c5c931b-7497-4ff9-abd1-5d00f9a5622b", "sort": "3009174000", "src": "ld", "section": "idioms", "stems": ["if you must know"], "offensive": false}, "hwi": {"hw": "if you must know"}, "fl": "idiom", "def": [{"sseq": [[["sense", {"dt": [["uns", [[["text", "used when one is answering a question that one does not want to answer because the information is personal, embarrassing, etc. "], ["vis", [{"t": "\"Why did you leave that job?\" \"{it}If you must know{/it}, I was fired.\""}]]]]]]}]]]}], "shortdef": ["\u2014used when one is answering a question that one does not want to answer because the information is personal, embarrassing, etc."]}, {"meta": {"id": "I must love you and leave you", "uuid": "a91a3907-c303-4b6f-909e-ca8ff7326c73", "sort": "3009236000", "src": "ld", "section": "idioms", "stems": ["i must love you and leave you"], "offensive": false}, "hwi": {"hw": "I must love you and leave you"}, "fl": "idiom", "def": [{"sls": ["British", "informal"], "sseq": [[["sense", {"dt": [["uns", [[["text", "used to say that one has to leave "], ["vis", [{"t": "I don't want to miss the last train, so I'm afraid {it}I must love you and leave you{/it}."}]]]]]]}]]]}], "shortdef": ["\u2014used to say that one has to leave"]}]