[{"meta": {"id": "plumy", "uuid": "0bb5a0cc-7a25-4674-a5ad-88c11cfac78f", "sort": "165238000", "src": "collegiate", "section": "alpha", "stems": ["plumier", "plumiest", "plumy"], "offensive": false}, "hwi": {"hw": "plumy", "prs": [{"mw": "\u02c8pl\u00fc-m\u0113", "sound": {"audio": "plumy001", "ref": "c", "stat": "1"}}]}, "fl": "adjective", "ins": [{"if": "plum*i*er"}, {"ifc": "-est", "if": "plum*i*est"}], "def": [{"sseq": [[["sense", {"sn": "1", "dt": [["text", "{bc}{sx|downy||}"]]}]], [["sense", {"sn": "2", "dt": [["text", "{bc}having or resembling {a_link|plumes}"]]}]]]}], "date": "1582{ds||1||}", "shortdef": ["downy", "having or resembling plumes"]}]