[{"meta": {"id": "repulsive", "uuid": "8c2eda7a-759f-4325-bec9-247ae6f2f2d0", "sort": "182317000", "src": "collegiate", "section": "alpha", "stems": ["repulsive", "repulsively", "repulsiveness", "repulsivenesses"], "offensive": false}, "hwi": {"hw": "re*pul*sive", "prs": [{"mw": "ri-\u02c8p\u0259l-siv", "sound": {"audio": "repuls03", "ref": "c", "stat": "1"}}]}, "fl": "adjective", "def": [{"sseq": [[["sense", {"sn": "1", "dt": [["text", "{bc}serving or able to {a_link|repulse} "], ["vis", [{"t": "{wi}repulsive{/wi} force"}]]]}]], [["sense", {"sn": "2", "dt": [["text", "{bc}tending to repel or reject {bc}{sx|cold||}, {sx|forbidding||}"]]}]], [["sense", {"sn": "3", "dt": [["text", "{bc}arousing aversion or disgust "], ["vis", [{"t": "{wi}repulsive{/wi} crimes"}]]]}]]]}], "uros": [{"ure": "re*pul*sive*ly", "fl": "adverb"}, {"ure": "re*pul*sive*ness", "fl": "noun"}], "et": [["text", "Middle English {it}repulsyve{/it} {ldquo}(in medicine) dissipating collected humors,{rdquo} borrowed from Middle French & Medieval Latin; Middle French {it}repulsif{/it} {ldquo}repelling, dissipating humors,{rdquo} borrowed from Medieval Latin {it}repuls\u012bvus,{/it} from Latin {it}repulsus,{/it} past participle of {it}repellere{/it} {ldquo}to push away, drive back, fend off{rdquo} + {it}-\u012bvus{/it} {et_link|-ive|-ive} {ma}{mat|repel|}{/ma}"]], "date": "1594{ds||1||}", "shortdef": ["serving or able to repulse", "tending to repel or reject : cold, forbidding", "arousing aversion or disgust"]}]