[{"meta": {"id": "revise:1", "uuid": "7536cfbf-29dc-4133-a05d-103c65deb655", "sort": "182902000", "src": "collegiate", "section": "alpha", "stems": ["revise", "revises"], "offensive": false}, "hom": 1, "hwi": {"hw": "re*vise", "prs": [{"mw": "\u02c8r\u0113-\u02ccv\u012bz", "sound": {"audio": "revise01", "ref": "c", "stat": "1"}}, {"mw": "ri-\u02c8v\u012bz"}]}, "fl": "noun", "def": [{"sseq": [[["sense", {"sn": "1", "dt": [["text", "{bc}an act of {a_link|revising} {bc}{sx|revision||}"]]}]], [["sense", {"sn": "2", "dt": [["text", "{bc}a printing proof that incorporates changes marked in a previous proof"]]}]]]}], "date": "1591{ds||1||}", "shortdef": ["an act of revising : revision", "a printing proof that incorporates changes marked in a previous proof"]}, {"meta": {"id": "revise:2", "uuid": "5957ef5e-6823-4e3a-87cd-40cda602fec7", "sort": "182903000", "src": "collegiate", "section": "alpha", "stems": ["revisable", "revise", "revised", "reviser", "revisers", "revises", "revising", "revisor", "revisors"], "offensive": false}, "hom": 2, "hwi": {"hw": "re*vise", "prs": [{"mw": "ri-\u02c8v\u012bz", "sound": {"audio": "revise02", "ref": "c", "stat": "1"}}]}, "fl": "verb", "ins": [{"if": "re*vised"}, {"if": "re*vis*ing"}], "def": [{"vd": "transitive verb", "sseq": [[["sense", {"sn": "1 a", "dt": [["text", "{bc}to look over again in order to correct or improve "], ["vis", [{"t": "{wi}revise{/wi} a manuscript"}]]]}], ["sense", {"sn": "b", "sls": ["British"], "dt": [["text", "{bc}to study again {bc}{sx|review||}"]]}]], [["sense", {"sn": "2 a", "dt": [["text", "{bc}to make a new, amended, improved, or up-to-date version of "], ["vis", [{"t": "{wi}revise{/wi} a dictionary"}]]]}], ["sense", {"sn": "b", "dt": [["text", "{bc}to provide with a new taxonomic arrangement "], ["vis", [{"t": "{it}revising{/it} the alpine ferns"}]]]}]]]}, {"vd": "intransitive verb", "sseq": [[["sense", {"sls": ["British"], "dt": [["text", "{bc}{sx|review||1}"]]}]]]}], "uros": [{"ure": "re*vis*able", "prs": [{"mw": "ri-\u02c8v\u012b-z\u0259-b\u0259l", "sound": {"audio": "revise03", "ref": "c", "stat": "1"}}], "fl": "adjective"}, {"ure": "re*vis*er", "vrs": [{"vl": "or", "va": "re*vi*sor", "prs": [{"mw": "ri-\u02c8v\u012b-z\u0259r", "sound": {"audio": "revise04", "ref": "c", "stat": "1"}}]}], "fl": "noun"}], "syns": [{"pl": "synonyms", "pt": [["text", "{sc}correct{/sc} {sc}rectify{/sc} {sc}emend{/sc} {sc}remedy{/sc} {sc}redress{/sc} {sc}amend{/sc} {sc}reform{/sc} {sc}revise{/sc} mean to make right what is wrong. {sc}correct{/sc} implies taking action to remove errors, faults, deviations, defects. "], ["vis", [{"t": "{it}correct{/it} your spelling"}]], ["text", " {sc}rectify{/sc} implies a more essential changing to make something right, just, or properly controlled or directed. "], ["vis", [{"t": "{it}rectify{/it} a misguided policy"}]], ["text", " {sc}emend{/sc} specifically implies correction of a text or manuscript. "], ["vis", [{"t": "{it}emend{/it} a text"}]], ["text", " {sc}remedy{/sc} implies removing or making harmless a cause of trouble, harm, or evil. "], ["vis", [{"t": "set out to {it}remedy{/it} the evils of the world"}]], ["text", " {sc}redress{/sc} implies making compensation or reparation for an unfairness, injustice, or imbalance. "], ["vis", [{"t": "{it}redress{/it} past social injustices"}]], ["text", " {sc}amend{/sc} {sc}reform{/sc} {sc}revise{/sc} imply an improving by making corrective changes, {sc}amend{/sc} usually suggesting slight changes "], ["vis", [{"t": "{it}amend{/it} a law"}]], ["text", ", {sc}reform{/sc} implying drastic change "], ["vis", [{"t": "plans to {it}reform{/it} the court system"}]], ["text", ", and {sc}revise{/sc} suggesting a careful examination of something and the making of necessary changes. "], ["vis", [{"t": "{it}revise{/it} the schedule"}]]]}], "et": [["text", "Middle French {it}reviser{/it}, from Latin {it}revisere{/it} to look at again, frequentative of {it}revid\u0113re{/it} to see again, from {it}re-{/it} + {it}vid\u0113re{/it} to see {ma}{mat|wit|}{/ma}"]], "date": "1545{ds|t|1|a|}", "shortdef": ["to look over again in order to correct or improve", "to study again : review", "to make a new, amended, improved, or up-to-date version of"]}]