[{"meta": {"id": "rigor", "uuid": "6f6622c3-e4e7-4c73-8c6c-7ce0dcb0723f", "sort": "183282000", "src": "collegiate", "section": "alpha", "stems": ["rigor", "rigors"], "offensive": false}, "hwi": {"hw": "rig*or", "prs": [{"mw": "\u02c8ri-g\u0259r", "sound": {"audio": "rigor001", "ref": "c", "stat": "1"}}]}, "fl": "noun", "def": [{"sseq": [[["pseq", [["sense", {"sn": "1 a (1)", "dt": [["text", "{bc}harsh inflexibility in opinion, temper, or judgment {bc}{sx|severity||} "], ["vis", [{"t": "The least one might observe is that this muddle of moralism and laxity, extreme {wi}rigor{/wi} and casual permissiveness, arduous altruism and nonchalant selfishness, has consequences.", "aq": {"auth": "Peter Berkowitz"}}]]]}], ["sense", {"sn": "(2)", "dt": [["text", "{bc}the quality of being unyielding or inflexible {bc}{sx|strictness||} "], ["vis", [{"t": "Their abandonment of this terminology is part of an effort to soften the {wi}rigor{/wi} of some of the rigid consequences thought to flow from the mechanical application of this dichotomy.", "aq": {"auth": "John D. Calamari and Joseph M. Perillo"}}]]]}], ["sense", {"sn": "(3)", "dt": [["text", "{bc}severity of life {bc}{sx|austerity||} "], ["vis", [{"t": "\u2026 a moral {wi}rigor{/wi} and growth that might help this country.", "aq": {"auth": "Stanley Kauffmann"}}]]]}]]], ["sense", {"sn": "b", "dt": [["text", "{bc}an act or instance of strictness, severity, or cruelty "], ["vis", [{"t": "\u2026 the humanist must recognize the normality, the practical necessity of the very {wi}rigors{/wi} he is trying to soften and correct.", "aq": {"auth": "Hermann J. Muller"}}]]]}]], [["sense", {"sn": "2", "dt": [["text", "{bc}a tremor caused by a chill "], ["vis", [{"t": "This young woman presented at the hospital with severe abdominal pain and signs of infection, including fever, {wi}rigor{/wi}, and leukocytosis.", "aq": {"auth": "Robert E. Scully et al."}}]]]}]], [["sense", {"sn": "3", "dt": [["text", "{bc}a condition that makes life difficult, challenging, or uncomfortable"]], "sdsense": {"sd": "especially", "dt": [["text", "{bc}extremity of cold "], ["vis", [{"t": "the {wi}rigors{/wi} of a New England winter"}]]]}}]], [["sense", {"sn": "4", "dt": [["text", "{bc}strict precision {bc}{sx|exactness||} "], ["vis", [{"t": "logical {wi}rigor{/wi}"}, {"t": "Tentatively one might suggest that what characterizes science is the {wi}rigor{/wi} of its methodology \u2026", "aq": {"auth": "Ernst Mayr"}}]]]}]], [["sense", {"sn": "5 a", "sls": ["obsolete"], "dt": [["text", "{bc}{sx|rigidity||}, {sx|stiffness||}"]]}], ["sense", {"sn": "b", "dt": [["text", "{bc}rigidness or torpor of organs or tissue that prevents response to stimuli"]]}], ["sense", {"sn": "c", "dt": [["text", "{bc}{sx|rigor mortis||} "], ["vis", [{"t": "A fish has its best flavor and texture when cooked while just coming out of {wi}rigor{/wi}.", "aq": {"auth": "Jane Daniels Lear"}}]]]}]]]}], "et": [["text", "Middle English {it}rigour{/it}, from Anglo-French, from Latin {it}rigor{/it}, literally, stiffness, from {it}rig\u0113re{/it} to be stiff"]], "date": "14th century{ds||1|a|1}", "shortdef": ["harsh inflexibility in opinion, temper, or judgment : severity", "the quality of being unyielding or inflexible : strictness", "severity of life : austerity"]}]