[{"meta": {"id": "roll-off", "uuid": "d1f387cf-5d10-44d5-84cd-d0aa0273251f", "sort": "183694000", "src": "collegiate", "section": "alpha", "stems": ["roll-off", "roll-offs"], "offensive": false}, "hwi": {"hw": "roll-off", "prs": [{"mw": "\u02c8r\u014dl-\u02cc\u022ff", "sound": {"audio": "rollof01", "ref": "c", "stat": "1"}}]}, "fl": "noun", "def": [{"sseq": [[["sense", {"dt": [["text", "{bc}a playoff match in bowling"]]}]]]}], "date": "1886", "shortdef": ["a playoff match in bowling"]}, {"meta": {"id": "roll/trip off the tongue", "uuid": "457869d3-017e-4cf5-8250-3cb8bd1e218c", "sort": "3016367000", "src": "ld", "section": "idioms", "stems": ["roll off the tongue", "roll/trip off the tongue", "trip off the tongue"], "offensive": false}, "hwi": {"hw": "roll/trip off the tongue"}, "fl": "idiom", "def": [{"sseq": [[["sense", {"dt": [["text", "{bc}to be easy to say or pronounce "], ["vis", [{"t": "The name just {it}rolls off the tongue{/it}."}]]]}]]]}], "shortdef": ["to be easy to say or pronounce"]}]