[{"meta": {"id": "romanize", "uuid": "488e4e4e-9e17-4506-8d39-81bc8bbc4c50", "sort": "183731000", "src": "collegiate", "section": "alpha", "stems": ["romanization", "romanizations", "romanize", "romanized", "romanizes", "romanizing"], "offensive": false}, "hwi": {"hw": "ro*man*ize", "prs": [{"mw": "\u02c8r\u014d-m\u0259-\u02ccn\u012bz", "sound": {"audio": "romani06", "ref": "c", "stat": "1"}}]}, "fl": "verb", "ins": [{"ifc": "-ized", "if": "ro*man*ized"}, {"ifc": "-iz*ing", "if": "ro*man*iz*ing"}], "def": [{"vd": "transitive verb", "sseq": [[["sense", {"sn": "1", "lbs": ["often capitalized"], "dt": [["text", "{bc}to make Roman in character"]]}]], [["sense", {"sn": "2", "dt": [["text", "{bc}to write or print (something, such as a language) in the Latin alphabet "], ["vis", [{"t": "{wi}romanize{/wi} Chinese"}]]]}]], [["sen", {"sn": "3", "lbs": ["capitalized"]}], ["sense", {"sn": "a", "dt": [["text", "{bc}to convert to Roman Catholicism"]]}], ["sense", {"sn": "b", "dt": [["text", "{bc}to give a Roman Catholic character to"]]}]]]}], "uros": [{"ure": "ro*man*i*za*tion", "prs": [{"mw": "\u02ccr\u014d-m\u0259-n\u0259-\u02c8z\u0101-sh\u0259n", "sound": {"audio": "romani07", "ref": "c", "stat": "1"}}], "fl": "noun", "lbs": ["often capitalized"]}], "date": "1607{ds||1||}", "shortdef": ["to make Roman in character", "to write or print (something, such as a language) in the Latin alphabet", "to convert to Roman Catholicism"]}]