[{"meta": {"id": "subluxation", "uuid": "6c2f0095-0665-4cf2-a6ad-1ead931f97b3", "sort": "194898300", "src": "collegiate", "section": "alpha", "stems": ["subluxation", "subluxations"], "offensive": false}, "hwi": {"hw": "sub*lux*a*tion", "prs": [{"mw": "\u02ccs\u0259-\u02ccbl\u0259k-\u02c8s\u0101-sh\u0259n", "sound": {"audio": "sublux01", "ref": "c", "stat": "1"}}]}, "fl": "noun", "def": [{"sseq": [[["sense", {"dt": [["text", "{bc}partial dislocation (as of one of the bones in a joint)"]]}]]]}], "date": "1634", "shortdef": ["partial dislocation (as of one of the bones in a joint)"]}]