[{"meta": {"id": "submerse", "uuid": "1633be10-ddb7-4735-b6a4-008f547c34e6", "sort": "194899600", "src": "collegiate", "section": "alpha", "stems": ["submerse", "submersed", "submerses", "submersing", "submersion", "submersions"], "offensive": false}, "hwi": {"hw": "sub*merse", "prs": [{"mw": "s\u0259b-\u02c8m\u0259rs", "sound": {"audio": "submer04", "ref": "c", "stat": "1"}}]}, "fl": "verb", "ins": [{"if": "sub*mersed"}, {"if": "sub*mers*ing"}], "def": [{"vd": "transitive verb", "sseq": [[["sense", {"dt": [["text", "{bc}{sx|submerge||}"]]}]]]}], "uros": [{"ure": "sub*mer*sion", "prs": [{"mw": "s\u0259b-\u02c8m\u0259r-zh\u0259n", "sound": {"audio": "submer05", "ref": "c", "stat": "1"}}, {"mw": "-sh\u0259n"}], "fl": "noun"}], "et": [["text", "Latin {it}submersus{/it}, past participle of {it}submergere{/it}"]], "date": "15th century", "shortdef": ["submerge"]}]