[{"meta": {"id": "thereunto", "uuid": "cb4712e5-2b8c-4f69-b92a-3c0d93227a93", "sort": "200154100", "src": "collegiate", "section": "alpha", "stems": ["thereunto"], "offensive": false}, "hwi": {"hw": "there*un*to", "prs": [{"mw": "t\u035fher-\u02c8\u0259n-(\u02cc)t\u00fc", "sound": {"audio": "thereu02", "ref": "c", "stat": "1"}}, {"mw": "\u02cct\u035fher-\u0259n-\u02c8t\u00fc"}]}, "fl": "adverb", "def": [{"sls": ["archaic"], "sseq": [[["sense", {"dt": [["text", "{bc}{sx|thereto||}"]]}]]]}], "date": "14th century", "shortdef": ["thereto"]}]