[{"meta": {"id": "unpleasantness", "uuid": "ed98457d-a79b-4480-91b6-ba3d8f8d5944", "sort": "211814000", "src": "collegiate", "section": "alpha", "stems": ["unpleasantness", "unpleasantnesses"], "offensive": false}, "hwi": {"hw": "un*pleas*ant*ness", "prs": [{"mw": "\u02cc\u0259n-\u02c8ple-z\u1d4ant-n\u0259s", "sound": {"audio": "unpleasantness_1", "ref": "owl", "stat": "1"}}]}, "fl": "noun", "def": [{"sseq": [[["sense", {"sn": "1", "dt": [["text", "{bc}the quality or state of being {a_link|unpleasant}"]]}]], [["sense", {"sn": "2", "dt": [["text", "{bc}an unpleasant situation, experience, or event"]]}]]]}], "date": "1546{ds||1||}", "shortdef": ["the quality or state of being unpleasant", "an unpleasant situation, experience, or event"]}]