[{"meta": {"id": "windowsill", "uuid": "d01afbbd-9ef4-4c84-ad82-3ac4219b00a4", "sort": "230173200", "src": "collegiate", "section": "alpha", "stems": ["windowsill", "windowsills"], "offensive": false}, "hwi": {"hw": "win*dow*sill", "prs": [{"mw": "\u02c8win-d\u014d-\u02ccsil", "sound": {"audio": "window07", "ref": "c", "stat": "1"}}, {"mw": "-d\u0259-"}]}, "fl": "noun", "def": [{"sseq": [[["sense", {"dt": [["text", "{bc}the horizontal member at the bottom of a {a_link|window} opening"]]}]]]}], "date": "1703", "shortdef": ["the horizontal member at the bottom of a window opening"]}]